hhack/__init__.py
hhack/cli.py
hhack/config.py
hhack/core.py
hhack/dataset.py
hhack/example.py
hhack/llm_handlers.py
hhack/main.py
hhack-0.1.4.dist-info/WHEEL
hhack-0.1.4.dist-info/entry_points.txt
hhack-0.1.4.dist-info/METADATA
hhack-0.1.4.dist-info/RECORD
