Metadata-Version: 2.3
Name: hhack
Version: 0.1.4
Summary: Add your description here
Author: Abdul Hadi
Author-email: Abdul Hadi <abdulhadih48@gmail.com>
Requires-Dist: matplotlib>=3.10.5
Requires-Dist: requests>=2.32.5
Requires-Dist: torch>=1.9.0 ; extra == 'full-local'
Requires-Dist: transformers>=4.20.0 ; extra == 'full-local'
Requires-Dist: accelerate>=0.12.0 ; extra == 'full-local'
Requires-Dist: ollama>=0.1.0 ; extra == 'full-local'
Requires-Dist: kernels>=0.1.0 ; extra == 'full-local'
Requires-Dist: torch>=1.9.0 ; extra == 'local'
Requires-Dist: transformers>=4.20.0 ; extra == 'local'
Requires-Dist: kernels>=0.1.0 ; extra == 'local'
Requires-Dist: ollama>=0.1.0 ; extra == 'ollama'
Requires-Python: >=3.13
Provides-Extra: full-local
Provides-Extra: local
Provides-Extra: ollama
